MANIFEST.in
README
setup.py
TestLazynight.egg-info/PKG-INFO
TestLazynight.egg-info/SOURCES.txt
TestLazynight.egg-info/dependency_links.txt
TestLazynight.egg-info/entry_points.txt
TestLazynight.egg-info/requires.txt
TestLazynight.egg-info/top_level.txt
fabfile/__init__.py
test/__init__.py
test/log.py
test/main.py
test/settings.py