Metadata-Version: 1.0
Name: TestLazynight
Version: 3.11.27.1
Summary: HELLO README!
Home-page: http://read.sohu.com
Author: flowerowl
Author-email: lazynight@gmail.com
License: UNKNOWN
Platform: UNKNOWN
